Workbook

Sheet Resumen
A2: Estrategia de venta NFC para reseñas de Google
A3: Modelo base: Estándar S/50 y Premium S/70. Los resultados cambian al editar la hoja Costos y metas.
A5: Meta neta negocio | D5: Unidades requeridas | G5: Venta mensual estimada | J5: Utilidad por socio
A6: ='Costos y metas'!B20 -> 4000 | D6: ='Costos y metas'!E34 -> 75 | G6: ='Costos y metas'!G34 -> 5100 | J6: ='Costos y metas'!H34 -> 2012.5
A10: Economía por producto | H10: Producto | I10: Precio | J10: Margen
A11: Producto | B11: Precio | C11: Costo variable | D11: Margen unitario | E11: Margen % | F11: Unidades meta | H11: Estándar | I11: =B12 -> 60 | J11: =D12 -> 47
A12: Estándar | B12: ='Costos y metas'!B26 -> 60 | C12: ='Costos y metas'!E26 -> 13 | D12: ='Costos y metas'!F26 -> 47 | E12: ='Costos y metas'!G26 -> 0.78333333 | F12: ='Costos y metas'!E34*'Costos y metas'!B16 -> 45 | H12: Premium | I12: =B13 -> 80 | J12: =D13 -> 67
A13: Premium | B13: ='Costos y metas'!B27 -> 80 | C13: ='Costos y metas'!E27 -> 13 | D13: ='Costos y metas'!F27 -> 67 | E13: ='Costos y metas'!G27 -> 0.8375 | F13: ='Costos y metas'!E34*'Costos y metas'!B17 -> 30 | H13: Promedio | I13: =B14 -> 68 | J13: =D14 -> 55
A14: Promedio | B14: ='Costos y metas'!B28 -> 68 | C14: ='Costos y metas'!E28 -> 13 | D14: ='Costos y metas'!F28 -> 55 | E14: ='Costos y metas'!G28 -> 0.80882353 | F14: ='Costos y metas'!E34 -> 75
A17: Embudo mensual para llegar a la meta
A18: Etapa | B18: Cantidad objetivo | C18: Conversión / ratio | D18: Por día | E18: Acción | F18: Indicador
A19: Prospectos contactados | B19: =CEILING(B20/0.35,1) -> 595 | C19: ="" | D19: =B19/'Costos y metas'!B18 -> 24.791667 | E19: DM, WhatsApp y visitas | F19: Contactos
A20: Respuestas | B20: =CEILING(B21/0.7,1) -> 208 | C20: =B20/B19 -> 0.34957983 | D20: =B20/'Costos y metas'!B18 -> 8.6666667 | E20: Responder en menos de 10 min | F20: Respuestas
A21: Demostraciones | B21: =CEILING(B22/0.4,1) -> 145 | C21: =B21/B20 -> 0.69711538 | D21: =B21/'Costos y metas'!B18 -> 6.0416667 | E21: Video o prueba en vivo | F21: Demos
A22: Negocios compradores | B22: =CEILING(B23/1.3,1) -> 58 | C22: =B22/B21 -> 0.4 | D22: =B22/'Costos y metas'!B18 -> 2.4166667 | E22: Cerrar y cobrar | F22: Clientes
A23: Unidades vendidas | B23: ='Costos y metas'!E34 -> 75 | C23: =B23/B22 -> 1.2931034 | D23: =B23/'Costos y metas'!B18 -> 3.125 | E23: Configurar y entregar | F23: Unidades
A26: Prioridades de arranque
A27: # | B27: Área | C27: Acción | D27: Meta | E27: Plazo | F27: Estado
A28: 1 | B28: Oferta | C28: Vender instalación lista, no solo una tarjeta | D28: Estándar S/50 | Premium S/70 | E28: Semana 1 | F28: Pendiente
A29: 2 | B29: Demostración | C29: Video de 10–15 segundos mostrando el toque y la reseña | D29: 1 video vertical + 5 fotos | E29: Semana 1 | F29: Pendiente
A30: 3 | B30: Prospección | C30: Lista inicial de negocios con atención presencial | D30: 200 prospectos | E30: Semana 1 | F30: Pendiente
A31: 4 | B31: Validación | C31: Cerrar las primeras ventas y registrar objeciones | D31: 20 unidades | E31: Mes 1 | F31: Pendiente
A32: 5 | B32: Prueba social | C32: Grabar instalaciones y solicitar testimonio | D32: 5 casos reales | E32: Mes 1 | F32: Pendiente
A33: 6 | B33: Escala | C33: Invertir en anuncios solo después de medir conversión | D33: Costo por cliente rentable | E33: Mes 2 | F33: Pendiente

Sheet Costos y metas
A2: Costos, precios y metas
A3: Cambia únicamente las celdas amarillas. Las fórmulas recalculan márgenes, inversión y ventas necesarias.
A5: Supuestos editables | F5: Gastos fijos mensuales
A6: Concepto | B6: Valor | C6: Unidad | D6: Nota | F6: Concepto | G6: Monto | H6: Nota
A7: Costo unitario Estándar | B7: 13 | C7: S/ por unidad | D7: Costo de compra | F7: Publicidad | H7: Presupuesto de prueba
A8: Costo unitario Premium | B8: 13 | C8: S/ por unidad | D8: Costo de compra | F8: Movilidad para visitas | H8: Prospección presencial
A9: Empaque por unidad | C9: S/ por unidad | D9: Bolsa/caja/etiqueta | F9: Teléfono/datos | G9: 100 | H9: Parte atribuible al negocio
A10: Configuración y prueba | C10: S/ por unidad | D10: Valora tu tiempo | F10: Dominio/sistema | H10: Equivalente mensual inicial
A11: Comisión de cobro | B11: 0 | C11: % de venta | D11: Yape/Plin suele ser 0% | F11: Material de muestra | G11: 0 | H11: Se considera en inversión inicial
A12: Delivery asumido por ti | B12: 0 | C12: S/ por unidad | D12: Usa 0 si lo paga el cliente | F12: Otros | H12: Imprevistos
A13: Reserva por fallas | C13: S/ por unidad | D13: Cambios o unidades defectuosas | F13: Total gastos fijos | G13: =SUM(G7:G12) -> 100
A14: Precio Estándar | B14: 60 | C14: S/ por unidad | D14: Precio público
A15: Precio Premium | B15: 80 | C15: S/ por unidad | D15: Precio público
A16: Mezcla Estándar | B16: 0.6 | C16: % de unidades | D16: Estimación inicial
A17: Mezcla Premium | B17: =1-B16 -> 0.4 | C17: % de unidades | D17: Se calcula como 100% - Estándar
A18: Días de venta al mes | B18: 24 | C18: días | D18: Lunes a sábado aprox.
A19: Número de socios | B19: 2 | C19: personas | D19: Para repartir utilidad
A20: Meta utilidad del negocio | B20: 4000 | C20: S/ al mes | D20: Después de costos del negocio
A21: Meta personal por socio | B21: 4000 | C21: S/ al mes | D21: Escenario alternativo
A24: Economía por producto
A25: Producto | B25: Precio | C25: Costo compra | D25: Otros variables | E25: Costo variable total | F25: Margen unitario | G25: Margen % | H25: Punto de equilibrio
A26: Estándar | B26: =B14 -> 60 | C26: =B7 -> 13 | D26: =B9+B10+B12+B13+B14*B11 -> 0 | E26: =C26+D26 -> 13 | F26: =B26-E26 -> 47 | G26: =F26/B26 -> 0.78333333 | H26: =CEILING($G$13/F26,1) -> 3
A27: Premium | B27: =B15 -> 80 | C27: =B8 -> 13 | D27: =B9+B10+B12+B13+B15*B11 -> 0 | E27: =C27+D27 -> 13 | F27: =B27-E27 -> 67 | G27: =F27/B27 -> 0.8375 | H27: =CEILING($G$13/F27,1) -> 2
A28: Promedio según mezcla | B28: =B26*$B$16+B27*$B$17 -> 68 | C28: =C26*$B$16+C27*$B$17 -> 13 | D28: =D26*$B$16+D27*$B$17 -> 0 | E28: =E26*$B$16+E27*$B$17 -> 13 | F28: =F26*$B$16+F27*$B$17 -> 55 | G28: =F28/B28 -> 0.80882353 | H28: =CEILING($G$13/F28,1) -> 2
A31: Metas mensuales
A32: Escenario | B32: Meta neta | C32: Gastos fijos | D32: Margen promedio | E32: Unidades/mes | F32: Unidades/día | G32: Ventas estimadas | H32: Utilidad por socio
A33: Validación inicial | B33: =0 -> 0 | C33: =$G$13 -> 100 | D33: =$F$28 -> 55 | E33: 20 | F33: =E33/$B$18 -> 0.83333333 | G33: =E33*$B$28 -> 1360 | H33: =(E33*$F$28-C33)/$B$19 -> 500
A34: S/4,000 para el negocio | B34: =B20 -> 4000 | C34: =$G$13 -> 100 | D34: =$F$28 -> 55 | E34: =CEILING((B34+C34)/D34,1) -> 75 | F34: =E34/$B$18 -> 3.125 | G34: =E34*$B$28 -> 5100 | H34: =(E34*$F$28-C34)/$B$19 -> 2012.5
A35: S/4,000 para cada socio | B35: =B21*B19 -> 8000 | C35: =$G$13 -> 100 | D35: =$F$28 -> 55 | E35: =CEILING((B35+C35)/D35,1) -> 148 | F35: =E35/$B$18 -> 6.1666667 | G35: =E35*$B$28 -> 10064 | H35: =(E35*$F$28-C35)/$B$19 -> 4020
A38: Inversión inicial sugerida | F38: Promociones sugeridas
A39: Concepto | B39: Cantidad | C39: Costo unitario | D39: Total | F39: Oferta | G39: Precio | H39: Margen estimado
A40: Inventario Estándar | B40: 25 | C40: 13 | D40: =B40*C40 -> 325 | F40: 1 Estándar | G40: 60 | H40: =G40-$E$26 -> 47
A41: Inventario Premium | B41: 25 | C41: 13 | D41: =B41*C41 -> 325 | F41: 1 Premium | G41: 80 | H41: =G41-$E$27 -> 67
A42: Empaques | B42: 50 | C42: 2 | D42: =B42*C42 -> 100 | F42: 2 Estándar | G42: 100 | H42: =G42-2*$E$26 -> 74
A43: Unidades de muestra | B43: 2 | C43: 13 | D43: =B43*C43 -> 26 | F43: 1 Estándar + 1 Premium | G43: 120 | H43: =G43-$E$26-$E$27 -> 94
A44: Dominio anual | B44: 1 | C44: 110 | D44: =B44*C44 -> 110
A45: Publicidad de lanzamiento | B45: 1 | C45: 300 | D45: =B45*C45 -> 300
A46: Movilidad de lanzamiento | B46: 1 | C46: 200 | D46: =B46*C46 -> 200
A47: Imprevistos | B47: 1 | C47: 100 | D47: =B47*C47 -> 100
A48: Inversión inicial total | D48: =SUM(D40:D47) -> 1486

Sheet Plan 30 dias
A2: Plan de acción de 30 días
A3: Objetivo: validar demanda, lograr 20 unidades y construir evidencia real antes de escalar publicidad.
A5: Día | B5: Semana | C5: Acción principal | D5: Meta medible | E5: Canal | F5: Responsable | G5: Estado | H5: Resultado / aprendizaje
A6: 1 | B6: 1 | C6: Definir oferta, precios y condiciones | D6: Oferta final escrita | E6: Gestión | F6: Kevin / Luis | G6: Pendiente
A7: 2 | B7: 1 | C7: Configurar 2 muestras con negocios de prueba | D7: 2 muestras funcionando | E7: Producto | F7: Kevin / Luis | G7: Pendiente
A8: 3 | B8: 1 | C8: Grabar video demostrativo vertical | D8: 1 video de 10–15 s | E8: Contenido | F8: Kevin / Luis | G8: Pendiente
A9: 4 | B9: 1 | C9: Tomar fotos claras de ambos modelos | D9: 5 fotos utilizables | E9: Contenido | F9: Kevin / Luis | G9: Pendiente
A10: 5 | B10: 1 | C10: Crear catálogo de WhatsApp y perfiles | D10: Catálogo publicado | E10: Digital | F10: Kevin / Luis | G10: Pendiente
A11: 6 | B11: 1 | C11: Preparar guion de venta y respuestas | D11: 1 guion + 8 objeciones | E11: Ventas | F11: Kevin / Luis | G11: Pendiente
A12: 7 | B12: 1 | C12: Construir lista de prospectos | D12: 50 negocios | E12: Prospección | F12: Kevin / Luis | G12: Pendiente
A13: 8 | B13: 2 | C13: Contactar negocios por Instagram/WhatsApp | D13: 15 contactos | E13: Mensajes | F13: Kevin / Luis | G13: Pendiente
A14: 9 | B14: 2 | C14: Visitar negocios cercanos con muestra | D14: 5 visitas | E14: Presencial | F14: Kevin / Luis | G14: Pendiente
A15: 10 | B15: 2 | C15: Dar seguimiento a interesados | D15: 10 seguimientos | E15: Mensajes | F15: Kevin / Luis | G15: Pendiente
A16: 11 | B16: 2 | C16: Contactar nuevos prospectos | D16: 15 contactos | E16: Mensajes | F16: Kevin / Luis | G16: Pendiente
A17: 12 | B17: 2 | C17: Visitar segunda zona comercial | D17: 5 visitas | E17: Presencial | F17: Kevin / Luis | G17: Pendiente
... A35: 30 | B35: 5 | C35: Decidir: ajustar, mantener o escalar | D35: Plan del mes 2 | E35: Gestión | F35: Kevin / Luis | G35: Pendiente

Sheet Seguimiento ventas
A2: Seguimiento de prospectos y ventas
A3: Registra cada contacto. La conversión solo mejora si anotas el canal, el estado, el próximo paso y el resultado.
A5: Fecha | B5: Negocio | C5: Rubro | D5: Distrito | E5: Canal | F5: Contacto | G5: Estado | H5: Producto | I5: Cantidad | J5: Precio unitario | K5: Venta total | L5: Costo total | M5: Margen bruto | N5: Próximo paso | O5: Fecha seguimiento | P5: Notas
J6: =IF(H6="Estándar",'Costos y metas'!$B$14,IF(H6="Premium",'Costos y metas'!$B$15,IF(H6="Pack 2 Estándar",'Costos y metas'!$G$42,IF(H6="Pack mixto",'Costos y metas'!$G$43,"")))) | K6: =IF(OR(I6="",J6=""),"",I6*J6) | L6: =IF(H6="Estándar",I6*'Costos y metas'!$E$26,IF(H6="Premium",I6*'Costos y metas'!$E$27,IF(H6="Pack 2 Estándar",I6*2*'Costos y metas'!$E$26,IF(H6="Pack mixto",I6*('Costos y metas'!$E$26+'Costos y metas'!$E$27),"")))) | M6: =IF(OR(K6="",L6=""),"",K6-L6)
J7: =IF(H7="Estándar",'Costos y metas'!$B$14,IF(H7="Premium",'Costos y metas'!$B$15,IF(H7="Pack 2 Estándar",'Costos y metas'!$G$42,IF(H7="Pack mixto",'Costos y metas'!$G$43,"")))) | K7: =IF(OR(I7="",J7=""),"",I7*J7) | L7: =IF(H7="Estándar",I7*'Costos y metas'!$E$26,IF(H7="Premium",I7*'Costos y metas'!$E$27,IF(H7="Pack 2 Estándar",I7*2*'Costos y metas'!$E$26,IF(H7="Pack mixto",I7*('Costos y metas'!$E$26+'Costos y metas'!$E$27),"")))) | M7: =IF(OR(K7="",L7=""),"",K7-L7)
J8: =IF(H8="Estándar",'Costos y metas'!$B$14,IF(H8="Premium",'Costos y metas'!$B$15,IF(H8="Pack 2 Estándar",'Costos y metas'!$G$42,IF(H8="Pack mixto",'Costos y metas'!$G$43,"")))) | K8: =IF(OR(I8="",J8=""),"",I8*J8) | L8: =IF(H8="Estándar",I8*'Costos y metas'!$E$26,IF(H8="Premium",I8*'Costos y metas'!$E$27,IF(H8="Pack 2 Estándar",I8*2*'Costos y metas'!$E$26,IF(H8="Pack mixto",I8*('Costos y metas'!$E$26+'Costos y metas'!$E$27),"")))) | M8: =IF(OR(K8="",L8=""),"",K8-L8)
J9: =IF(H9="Estándar",'Costos y metas'!$B$14,IF(H9="Premium",'Costos y metas'!$B$15,IF(H9="Pack 2 Estándar",'Costos y metas'!$G$42,IF(H9="Pack mixto",'Costos y metas'!$G$43,"")))) | K9: =IF(OR(I9="",J9=""),"",I9*J9) | L9: =IF(H9="Estándar",I9*'Costos y metas'!$E$26,IF(H9="Premium",I9*'Costos y metas'!$E$27,IF(H9="Pack 2 Estándar",I9*2*'Costos y metas'!$E$26,IF(H9="Pack mixto",I9*('Costos y metas'!$E$26+'Costos y metas'!$E$27),"")))) | M9: =IF(OR(K9="",L9=""),"",K9-L9)
J10: =IF(H10="Estándar",'Costos y metas'!$B$14,IF(H10="Premium",'Costos y metas'!$B$15,IF(H10="Pack 2 Estándar",'Costos y metas'!$G$42,IF(H10="Pack mixto",'Costos y metas'!$G$43,"")))) | K10: =IF(OR(I10="",J10=""),"",I10*J10) | L10: =IF(H10="Estándar",I10*'Costos y metas'!$E$26,IF(H10="Premium",I10*'Costos y metas'!$E$27,IF(H10="Pack 2 Estándar",I10*2*'Costos y metas'!$E$26,IF(H10="Pack mixto",I10*('Costos y metas'!$E$26+'Costos y metas'!$E$27),"")))) | M10: =IF(OR(K10="",L10=""),"",K10-L10)
J11: =IF(H11="Estándar",'Costos y metas'!$B$14,IF(H11="Premium",'Costos y metas'!$B$15,IF(H11="Pack 2 Estándar",'Costos y metas'!$G$42,IF(H11="Pack mixto",'Costos y metas'!$G$43,"")))) | K11: =IF(OR(I11="",J11=""),"",I11*J11) | L11: =IF(H11="Estándar",I11*'Costos y metas'!$E$26,IF(H11="Premium",I11*'Costos y metas'!$E$27,IF(H11="Pack 2 Estándar",I11*2*'Costos y metas'!$E$26,IF(H11="Pack mixto",I11*('Costos y metas'!$E$26+'Costos y metas'!$E$27),"")))) | M11: =IF(OR(K11="",L11=""),"",K11-L11)
J12: =IF(H12="Estándar",'Costos y metas'!$B$14,IF(H12="Premium",'Costos y metas'!$B$15,IF(H12="Pack 2 Estándar",'Costos y metas'!$G$42,IF(H12="Pack mixto",'Costos y metas'!$G$43,"")))) | K12: =IF(OR(I12="",J12=""),"",I12*J12) | L12: =IF(H12="Estándar",I12*'Costos y metas'!$E$26,IF(H12="Premium",I12*'Costos y metas'!$E$27,IF(H12="Pack 2 Estándar",I12*2*'Costos y metas'!$E$26,IF(H12="Pack mixto",I12*('Costos y metas'!$E$26+'Costos y metas'!$E$27),"")))) | M12: =IF(OR(K12="",L12=""),"",K12-L12)
J13: =IF(H13="Estándar",'Costos y metas'!$B$14,IF(H13="Premium",'Costos y metas'!$B$15,IF(H13="Pack 2 Estándar",'Costos y metas'!$G$42,IF(H13="Pack mixto",'Costos y metas'!$G$43,"")))) | K13: =IF(OR(I13="",J13=""),"",I13*J13) | L13: =IF(H13="Estándar",I13*'Costos y metas'!$E$26,IF(H13="Premium",I13*'Costos y metas'!$E$27,IF(H13="Pack 2 Estándar",I13*2*'Costos y metas'!$E$26,IF(H13="Pack mixto",I13*('Costos y metas'!$E$26+'Costos y metas'!$E$27),"")))) | M13: =IF(OR(K13="",L13=""),"",K13-L13)
J14: =IF(H14="Estándar",'Costos y metas'!$B$14,IF(H14="Premium",'Costos y metas'!$B$15,IF(H14="Pack 2 Estándar",'Costos y metas'!$G$42,IF(H14="Pack mixto",'Costos y metas'!$G$43,"")))) | K14: =IF(OR(I14="",J14=""),"",I14*J14) | L14: =IF(H14="Estándar",I14*'Costos y metas'!$E$26,IF(H14="Premium",I14*'Costos y metas'!$E$27,IF(H14="Pack 2 Estándar",I14*2*'Costos y metas'!$E$26,IF(H14="Pack mixto",I14*('Costos y metas'!$E$26+'Costos y metas'!$E$27),"")))) | M14: =IF(OR(K14="",L14=""),"",K14-L14)
J15: =IF(H15="Estándar",'Costos y metas'!$B$14,IF(H15="Premium",'Costos y metas'!$B$15,IF(H15="Pack 2 Estándar",'Costos y metas'!$G$42,IF(H15="Pack mixto",'Costos y metas'!$G$43,"")))) | K15: =IF(OR(I15="",J15=""),"",I15*J15) | L15: =IF(H15="Estándar",I15*'Costos y metas'!$E$26,IF(H15="Premium",I15*'Costos y metas'!$E$27,IF(H15="Pack 2 Estándar",I15*2*'Costos y metas'!$E$26,IF(H15="Pack mixto",I15*('Costos y metas'!$E$26+'Costos y metas'!$E$27),"")))) | M15: =IF(OR(K15="",L15=""),"",K15-L15)
J16: =IF(H16="Estándar",'Costos y metas'!$B$14,IF(H16="Premium",'Costos y metas'!$B$15,IF(H16="Pack 2 Estándar",'Costos y metas'!$G$42,IF(H16="Pack mixto",'Costos y metas'!$G$43,"")))) | K16: =IF(OR(I16="",J16=""),"",I16*J16) | L16: =IF(H16="Estándar",I16*'Costos y metas'!$E$26,IF(H16="Premium",I16*'Costos y metas'!$E$27,IF(H16="Pack 2 Estándar",I16*2*'Costos y metas'!$E$26,IF(H16="Pack mixto",I16*('Costos y metas'!$E$26+'Costos y metas'!$E$27),"")))) | M16: =IF(OR(K16="",L16=""),"",K16-L16)
J17: =IF(H17="Estándar",'Costos y metas'!$B$14,IF(H17="Premium",'Costos y metas'!$B$15,IF(H17="Pack 2 Estándar",'Costos y metas'!$G$42,IF(H17="Pack mixto",'Costos y metas'!$G$43,"")))) | K17: =IF(OR(I17="",J17=""),"",I17*J17) | L17: =IF(H17="Estándar",I17*'Costos y metas'!$E$26,IF(H17="Premium",I17*'Costos y metas'!$E$27,IF(H17="Pack 2 Estándar",I17*2*'Costos y metas'!$E$26,IF(H17="Pack mixto",I17*('Costos y metas'!$E$26+'Costos y metas'!$E$27),"")))) | M17: =IF(OR(K17="",L17=""),"",K17-L17)
... J205: =IF(H205="Estándar",'Costos y metas'!$B$14,IF(H205="Premium",'Costos y metas'!$B$15,IF(H205="Pack 2 Estándar",'Costos y metas'!$G$42,IF(H205="Pack mixto",'Costos y metas'!$G$43,"")))) | K205: =IF(OR(I205="",J205=""),"",I205*J205) | L205: =IF(H205="Estándar",I205*'Costos y metas'!$E$26,IF(H205="Premium",I205*'Costos y metas'!$E$27,IF(H205="Pack 2 Estándar",I205*2*'Costos y metas'!$E$26,IF(H205="Pack mixto",I205*('Costos y metas'!$E$26+'Costos y metas'!$E$27),"")))) | M205: =IF(OR(K205="",L205=""),"",K205-L205)

Sheet Ingresos y gastos
A2: Control de ingresos y gastos
A3: Registra cada movimiento real del negocio. Los totales, la utilidad, el saldo y la utilidad por socio se calculan automáticamente.
A5: Total ingresos | B5: Total gastos | C5: Utilidad neta | D5: Saldo inicial | E5: Saldo actual | F5: Utilidad por socio | H5: Resumen | I5: Monto
A6: =SUMIFS($E$11:$E$510,$B$11:$B$510,"Ingreso") -> 0 | B6: =SUMIFS($E$11:$E$510,$B$11:$B$510,"Gasto") -> 442.71 | C6: =A6-B6 -> -442.71 | D6: =0 -> 0 | E6: =D6+C6 -> -442.71 | F6: =IF('Costos y metas'!$B$19>0,C6/'Costos y metas'!$B$19,0) -> -221.355 | H6: Ingresos | I6: =A6 -> 0
H7: Gastos | I7: =B6 -> 442.71
A10: Fecha | B10: Tipo | C10: Categoría | D10: Descripción | E10: Monto | F10: Método de pago | G10: Socio / responsable | H10: Mes | I10: Impacto en caja | J10: Notas
A11: 46274 | B11: Gasto | C11: Compra de mercadería | D11: Tarjeta Google NFC Cuadrado | E11: 3.78 | F11: Tarjeta | G11: Luis | H11: =IF(A11="","",TEXT(A11,"mmm-yyyy")) -> sep-yyyy | I11: =IF(OR(B11="",E11=""),"",IF(B11="Ingreso",E11,-E11)) -> -3.78
A12: 46275 | B12: Gasto | C12: Compra de mercadería | D12: Tarjeta Google NFC L 2 Cuadrado 2 | E12: 50 | F12: Tarjeta | G12: Kevin | H12: =IF(A12="","",TEXT(A12,"mmm-yyyy")) -> sep-yyyy | I12: =IF(OR(B12="",E12=""),"",IF(B12="Ingreso",E12,-E12)) -> -50
A13: 46287 | B13: Gasto | C13: Compra de mercadería | D13: Tarjeta Google NFC L 15 Cuadrado 15 | E13: 388.93 | F13: Tarjeta | G13: Kevin | H13: =IF(A13="","",TEXT(A13,"mmm-yyyy")) -> sep-yyyy | I13: =IF(OR(B13="",E13=""),"",IF(B13="Ingreso",E13,-E13)) -> -388.93 | J13: Luis debe debitar 194,47 a finales de octubre
H14: =IF(A14="","",TEXT(A14,"mmm-yyyy")) | I14: =IF(OR(B14="",E14=""),"",IF(B14="Ingreso",E14,-E14))
H15: =IF(A15="","",TEXT(A15,"mmm-yyyy")) | I15: =IF(OR(B15="",E15=""),"",IF(B15="Ingreso",E15,-E15))
H16: =IF(A16="","",TEXT(A16,"mmm-yyyy")) | I16: =IF(OR(B16="",E16=""),"",IF(B16="Ingreso",E16,-E16))
H17: =IF(A17="","",TEXT(A17,"mmm-yyyy")) | I17: =IF(OR(B17="",E17=""),"",IF(B17="Ingreso",E17,-E17))
H18: =IF(A18="","",TEXT(A18,"mmm-yyyy")) | I18: =IF(OR(B18="",E18=""),"",IF(B18="Ingreso",E18,-E18))
H19: =IF(A19="","",TEXT(A19,"mmm-yyyy")) | I19: =IF(OR(B19="",E19=""),"",IF(B19="Ingreso",E19,-E19))
H20: =IF(A20="","",TEXT(A20,"mmm-yyyy")) | I20: =IF(OR(B20="",E20=""),"",IF(B20="Ingreso",E20,-E20))
H21: =IF(A21="","",TEXT(A21,"mmm-yyyy")) | I21: =IF(OR(B21="",E21=""),"",IF(B21="Ingreso",E21,-E21))
H22: =IF(A22="","",TEXT(A22,"mmm-yyyy")) | I22: =IF(OR(B22="",E22=""),"",IF(B22="Ingreso",E22,-E22))
H23: =IF(A23="","",TEXT(A23,"mmm-yyyy")) | I23: =IF(OR(B23="",E23=""),"",IF(B23="Ingreso",E23,-E23))
H24: =IF(A24="","",TEXT(A24,"mmm-yyyy")) | I24: =IF(OR(B24="",E24=""),"",IF(B24="Ingreso",E24,-E24))
H25: =IF(A25="","",TEXT(A25,"mmm-yyyy")) | I25: =IF(OR(B25="",E25=""),"",IF(B25="Ingreso",E25,-E25))
... H510: =IF(A510="","",TEXT(A510,"mmm-yyyy")) | I510: =IF(OR(B510="",E510=""),"",IF(B510="Ingreso",E510,-E510))
